setup.py
lmdb_sessions/__init__.py
lmdb_sessions/sessions.py
lmdb_sessions.egg-info/PKG-INFO
lmdb_sessions.egg-info/SOURCES.txt
lmdb_sessions.egg-info/dependency_links.txt
lmdb_sessions.egg-info/requires.txt
lmdb_sessions.egg-info/top_level.txt