Metadata-Version: 1.0
Name: lmdb-sessions
Version: 0.0.1
Summary: An LMDB based backend for CherryPy sessions
Home-page: https://github.com/tburmeister/lmdb_sessions
Author: Taylor Burmeister
Author-email: UNKNOWN
License: UNKNOWN
Platform: UNKNOWN
